CHANGELOG
LICENSE
MANIFEST.in
README.md
setup.py
calculon/Calculon.py
calculon/Consumer.py
calculon/Producer.py
calculon/__init__.py
calculon.egg-info/PKG-INFO
calculon.egg-info/SOURCES.txt
calculon.egg-info/dependency_links.txt
calculon.egg-info/top_level.txt
calculon/test/Calculon.py
calculon/test/__init__.py