Metadata-Version: 1.1
Name: calculon
Version: 1.1.1
Summary: Implementation of the producer-consumer patternwith customizable producer and consumer methods andan ability to choose thread/process model for execution.
Home-page: https://github.com/jango/calculon
Author: Nikita Pchelin
Author-email: nikita@pchelin.ca
License: UNKNOWN
Platform: UNKNOWN
Classifier: Classifier: Development Status :: 5 - Production/Stable
Classifier: Classifier: License :: OSI Approved :: MIT License
Classifier: Environment :: Console
Classifier: Intended Audience :: Developers
Classifier: Natural Language :: English
Classifier: Operating System :: POSIX
Classifier: Operating System :: Microsoft :: Windows
Classifier: Programming Language :: Python :: 2.7
Classifier: Topic :: System :: Distributed Computing
